[
  {
    "Titulo": "Moradia em banda na Travessa Amândio Oliveira, s/n, Nossa Senhora do Amparo, Póvoa de Lanhoso",
    "Link": "https://www.idealista.pt/imovel/34265308/",
    "Preco": "1.600€/mês",
    "detalhe do item": "T4 | 183 m² área bruta",
    "Descricao do item": "Moradia T4 para arrendamento – Póvoa de Lanhoso Apresentamos esta excelente moradia T4, localizada numa zona tranquila da Póvoa de Lanhoso, com ótimos acessos e uma vista desafogada. Distribuída por três pisos, esta casa destaca-se pelo conforto, funcionalidade e luminosidade: Rés do chão com hall de entrada acolhed",
    "id": "34265308",
    "tags": [],
    "agenciaNome": "Norberto Freitas - Remax United 2",
    "agenciaLink": "https://www.idealista.pt/pro/norberto-freitas---remax-united-2/",
    "precoOriginal": null,
    "descontoPercentual": null,
    "estacionamento": null,
    "tempoDestaque": null,
    "imagens": null,
    "tipologia": "T4",
    "areaBrutaM2": 183,
    "pisoResumo": null
  },
  {
    "Titulo": "Moradia independente na Rua Senhor dos Aflitos, Nossa Senhora do Amparo, Póvoa de Lanhoso",
    "Link": "https://www.idealista.pt/imovel/34373582/",
    "Preco": "800€/mês",
    "detalhe do item": "T2 | 134 m² área bruta",
    "Descricao do item": "Moradia T2 para venda Andar Moradia T2 para Arrendamento no Centro da Póvoa de Lanhoso – 800€/mês Apresentamos este acolhedor andar moradia T2, disponível para arrendamento, situado no rés do chão de uma moradia familiar no coração da vila da Póvoa de Lanhoso. Com uma localização privilegiada, este imóvel destaca-",
    "id": "34373582",
    "tags": [],
    "agenciaNome": "RE/MAX Grupo Somos Póvoa de Lanhoso",
    "agenciaLink": "https://www.idealista.pt/pro/remaxsomossatisfactor/",
    "precoOriginal": null,
    "descontoPercentual": null,
    "estacionamento": null,
    "tempoDestaque": null,
    "imagens": null,
    "tipologia": "T2",
    "areaBrutaM2": 134,
    "pisoResumo": null
  }
]